{
  "timestamp": "2026-04-26T14:45:13.453701+00:00",
  "processes": {
    "sentinel-daemon": {
      "name": "sentinel-daemon",
      "status": "offline",
      "triage": "CRITICAL",
      "pm2_status": "stopped",
      "pid": 0,
      "uptime": "00:00:00",
      "restart_count": 0,
      "memory": "0 MB",
      "cpu": "0%",
      "last_action": "Process not running in PM2",
      "incident_report": "Process is not registered with PM2",
      "incident_count": 0,
      "metrics": {},
      "forensic_history": [],
      "last_update": "2026-04-26T14:45:13.453585+00:00"
    },
    "horizon-scout": {
      "name": "horizon-scout",
      "status": "offline",
      "triage": "CRITICAL",
      "pm2_status": "stopped",
      "pid": 0,
      "uptime": "00:00:00",
      "restart_count": 0,
      "memory": "0 MB",
      "cpu": "0%",
      "last_action": "Process not running in PM2",
      "incident_report": "Process is not registered with PM2",
      "incident_count": 0,
      "metrics": {},
      "forensic_history": [],
      "last_update": "2026-04-26T14:45:13.453624+00:00"
    },
    "nexus-bridge": {
      "name": "nexus-bridge",
      "status": "offline",
      "triage": "CRITICAL",
      "pm2_status": "stopped",
      "pid": 0,
      "uptime": "00:00:00",
      "restart_count": 0,
      "memory": "0 MB",
      "cpu": "0%",
      "last_action": "Process not running in PM2",
      "incident_report": "Process is not registered with PM2",
      "incident_count": 0,
      "metrics": {},
      "forensic_history": [],
      "last_update": "2026-04-26T14:45:13.453635+00:00"
    },
    "ouroboros-agent": {
      "name": "ouroboros-agent",
      "status": "offline",
      "triage": "CRITICAL",
      "pm2_status": "stopped",
      "pid": 0,
      "uptime": "00:00:00",
      "restart_count": 0,
      "memory": "0 MB",
      "cpu": "0%",
      "last_action": "Process not running in PM2",
      "incident_report": "Process is not registered with PM2",
      "incident_count": 0,
      "metrics": {},
      "forensic_history": [],
      "last_update": "2026-04-26T14:45:13.453646+00:00"
    },
    "bridge-agent": {
      "name": "bridge-agent",
      "status": "offline",
      "triage": "CRITICAL",
      "pm2_status": "stopped",
      "pid": 0,
      "uptime": "00:00:00",
      "restart_count": 0,
      "memory": "0 MB",
      "cpu": "0%",
      "last_action": "Process not running in PM2",
      "incident_report": "Process is not registered with PM2",
      "incident_count": 0,
      "metrics": {},
      "forensic_history": [],
      "last_update": "2026-04-26T14:45:13.453655+00:00"
    },
    "live-monitor": {
      "name": "live-monitor",
      "status": "offline",
      "triage": "CRITICAL",
      "pm2_status": "stopped",
      "pid": 0,
      "uptime": "00:00:00",
      "restart_count": 0,
      "memory": "0 MB",
      "cpu": "0%",
      "last_action": "Process not running in PM2",
      "incident_report": "Process is not registered with PM2",
      "incident_count": 0,
      "metrics": {},
      "forensic_history": [],
      "last_update": "2026-04-26T14:45:13.453664+00:00"
    },
    "logic-auditor": {
      "name": "logic-auditor",
      "status": "offline",
      "triage": "CRITICAL",
      "pm2_status": "stopped",
      "pid": 0,
      "uptime": "00:00:00",
      "restart_count": 0,
      "memory": "0 MB",
      "cpu": "0%",
      "last_action": "Process not running in PM2",
      "incident_report": "Process is not registered with PM2",
      "incident_count": 0,
      "metrics": {},
      "forensic_history": [],
      "last_update": "2026-04-26T14:45:13.453674+00:00"
    },
    "prime-director": {
      "name": "prime-director",
      "status": "offline",
      "triage": "CRITICAL",
      "pm2_status": "stopped",
      "pid": 0,
      "uptime": "00:00:00",
      "restart_count": 0,
      "memory": "0 MB",
      "cpu": "0%",
      "last_action": "Process not running in PM2",
      "incident_report": "Process is not registered with PM2",
      "incident_count": 0,
      "metrics": {},
      "forensic_history": [],
      "last_update": "2026-04-26T14:45:13.453683+00:00"
    }
  },
  "system": {
    "active_incidents": 8,
    "total_processes": 8,
    "healthy_processes": 0,
    "recovering_processes": 0,
    "critical_processes": 8,
    "last_update": "2026-04-26T14:45:13.453704+00:00",
    "observer_uptime": "00:01:18",
    "observer_pid": 37628
  }
}